typeddict/__init__.py
typeddict/__version__.py
typeddict/_pydantic.py
typeddict/fields.py
typeddict-0.2.0.dist-info/WHEEL
typeddict-0.2.0.dist-info/LICENSE
typeddict-0.2.0.dist-info/METADATA
typeddict-0.2.0.dist-info/RECORD
