Metadata-Version: 2.1
Name: typeddict
Version: 0.2.0
Summary: Use `TypedDict` replace pydantic definitions.
Home-page: https://github.com/abersheeran/typeddict
License: Apache-2.0
Author: abersheeran
Author-email: me@abersheeran.com
Requires-Python: >=3.7,<4.0
Classifier: License :: OSI Approved :: Apache Software License
Classifier: Programming Language :: Python :: 3
Classifier: Programming Language :: Python :: 3.7
Classifier: Programming Language :: Python :: 3.8
Classifier: Programming Language :: Python :: 3.9
Classifier: Programming Language :: Python :: 3.10
Classifier: Programming Language :: Python :: 3.11
Classifier: Programming Language :: Python :: 3
Requires-Dist: pydantic (>=1.9.1,<2.0.0)
Requires-Dist: typing-extensions (>=4.3.0)
Project-URL: Repository, https://github.com/abersheeran/typeddict
